README.md
setup.py
servusdates/__init__.py
servusdates/servusdates.py
servusdates.egg-info/PKG-INFO
servusdates.egg-info/SOURCES.txt
servusdates.egg-info/dependency_links.txt
servusdates.egg-info/requires.txt
servusdates.egg-info/top_level.txt